autoslugged/__init__.py
autoslugged/fields.py
autoslugged/models.py
autoslugged/settings.py
autoslugged/utils.py
django_autoslugged-2.0.0.post0.dist-info/AUTHORS.rst
django_autoslugged-2.0.0.post0.dist-info/COPYING.LESSER
django_autoslugged-2.0.0.post0.dist-info/METADATA
django_autoslugged-2.0.0.post0.dist-info/WHEEL
django_autoslugged-2.0.0.post0.dist-info/top_level.txt
django_autoslugged-2.0.0.post0.dist-info/RECORD
