Metadata-Version: 2.1
Name: django-autoslugged
Version: 2.0.0.post0
Summary: An automated slug field for Django.
Home-page: https://github.com/mbourqui/django-autoslugged/
Author: Marc Bourqui
Author-email: pypi.kemar@bourqui.org
License: GNU Lesser General Public License (LGPL), Version 3
Download-URL: https://github.com/mbourqui/django-autoslugged/releases/tag/v2.0.0-post
Keywords: django field slug auto unique transliteration i18n
Platform: UNKNOWN
Classifier: Development Status :: 7 - Inactive
Classifier: Environment :: Web Environment
Classifier: Framework :: Django
Classifier: Framework :: Django :: 1.9
Classifier: Framework :: Django :: 1.10
Classifier: Framework :: Django :: 1.11
Classifier: Framework :: Django :: 2.0
Classifier: Intended Audience :: Developers
Classifier: License :: OSI Approved :: GNU Library or Lesser General Public License (LGPL)
Classifier: Programming Language :: Python
Classifier: Programming Language :: Python :: 2
Classifier: Programming Language :: Python :: 2.7
Classifier: Programming Language :: Python :: 3
Classifier: Programming Language :: Python :: 3.5
Classifier: Programming Language :: Python :: Implementation :: CPython
Classifier: Programming Language :: Python :: Implementation :: PyPy
Classifier: Topic :: Software Development :: Libraries :: Python Modules
Classifier: Topic :: Text Processing :: General
Requires: python (>= 2.7)
Requires: django (>= 1.7.10)
Provides-Extra: cyrillic
Requires-Dist: pytils (>=0.2) ; extra == 'cyrillic'
Provides-Extra: translitcodec
Requires-Dist: translitcodec (>=0.3) ; extra == 'translitcodec'
